LICENSE
MANIFEST.in
README.rst
setup.py
daploader/__init__.py
daploader/dapi.help
daploader/dapicli.py
daploader/daplint.py
daploader/dapver.py
daploader/licenses.py
daploader.egg-info/PKG-INFO
daploader.egg-info/SOURCES.txt
daploader.egg-info/dependency_links.txt
daploader.egg-info/entry_points.txt
daploader.egg-info/requires.txt
daploader.egg-info/top_level.txt
test/bar-1.0.0.dap
test/bar-1.0.0dev.dap
test/bar-1.0.1.dap
test/bar-1.0.2.dap
test/bz2.dap
test/foo-1.0.0dev.dap
test/foo-1.0.1.dap
test/no_meta.dap
test/test_dap.py
test/test_dapicli.py
test/test_dapver.py
test/empty_dirs/foo-1.0.0.dap
test/meta_only/bar.dap
test/meta_only/foo-1.0.0.dap
test/meta_only/foo.dap
test/no_toplevel/foo-1.0.0.dap
test/outside_toplevel/foo-1.0.0.dap
test/wrong_files/foo-1.0.0.dap