Metadata-Version: 1.1
Name: daploader
Version: 0.0.9
Summary: Dap archives loader and checker
Home-page: https://github.com/hroncok/daploader
Author: Miro Hrončok
Author-email: miro@hroncok.cz
License: GPLv2+
Keywords: devassiatnt,lint,dap
Platform: UNKNOWN
Classifier: Development Status :: 4 - Beta
Classifier: Intended Audience :: Developers
Classifier: License :: OSI Approved :: GNU General Public License v2 or later (GPLv2+)
Classifier: Operating System :: POSIX :: Linux
Classifier: Programming Language :: Python
Classifier: Programming Language :: Python :: 2
Classifier: Programming Language :: Python :: 2.6
Classifier: Programming Language :: Python :: 2.7
Classifier: Programming Language :: Python :: 3
Classifier: Programming Language :: Python :: 3.3
